{
  "required": true,
  "package": "me.constantindev.ccl.mixin",
  "compatibilityLevel": "JAVA_8",
  "mixins": [
    "AbstractBlockStateMixin",
    "AbstractClientPlayerEntityMixin",
    "BlockHitResultMixin",
    "BlockMixin",
    "ClientConnectionMixin",
    "ClientPlayerEntityMixin",
    "ClientPlayerInteractionManagerMixin",
    "ClientPlayNetworkHandlerMixin",
    "ClientWorldMixin",
    "EntityRendererMixin",
    "IdentifierMixin",
    "ItemStackMixin",
    "LivingEntityAccessor",
    "LivingEntityMixin",
    "LivingEntityRendererMixin",
    "MinecraftClientMixin",
    "PlayerEntityMixin",
    "PlayerListEntryMixin",
    "ScoreboardMixin",
    "ScreenMixin",
    "SessionAccessor",
    "SignBlockEntityRendererMixin",
    "TextRendererMixin",
    "gui.ChatScreenMixin",
    "gui.CreativeInventoryScreenMixin",
    "gui.EditGameRulesScreenMixin",
    "gui.EntryListWidgetMixin",
    "gui.GameRendererHook",
    "gui.HeldItemRendererMixin",
    "gui.InGameHudMixin",
    "gui.InGameOverlayRendererMixin",
    "gui.MultiplayerScreenMixin",
    "gui.MultiplayerServerListWidgetAccessor",
    "gui.ParticleManagerMixin",
    "gui.ScanningEntryMixin",
    "gui.ScreenMixin",
    "gui.SelectWorldScreenMixin",
    "gui.ServerEntryMixin",
    "gui.SplashScreenMixin",
    "gui.TitleScreenMixin",
    "gui.WorldRendererMixin",
    "packet.ChatMessageC2SPacketMixin",
    "packet.CombatEventS2CPacketMixin",
    "packet.EntitySpawnS2CPacketMixin",
    "packet.ExplosionS2CPacketMixin",
    "packet.LoginHelloC2SPacketMixin",
    "packet.PlayerMoveC2SPacketAccessor",
    "packet.PlayerPositionLookS2CPacketMixin",
    "packet.PlaySoundS2CPacketMixin",
    "packet.ResourcePackStatusC2SPacketMixin",
    "packet.SignEditorOpenS2CPacketMixin",
    "packet.WorldTimeUpdateS2CPacketMixin"
  ],
  "client": [],
  "server": [],
  "injectors": {
    "defaultRequire": 1
  }
}